ExcelJiaochengShiyongjiqiaoXilie/README.md
ExcelJiaochengShiyongjiqiaoXilie/__init__.py
ExcelJiaochengShiyongjiqiaoXilie/__main__.py
ExcelJiaochengShiyongjiqiaoXilie/file.epub
ExcelJiaochengShiyongjiqiaoXilie/index.html
ExcelJiaochengShiyongjiqiaoXilie/css/__init__.py
ExcelJiaochengShiyongjiqiaoXilie/css/annotations.css
ExcelJiaochengShiyongjiqiaoXilie/css/main.css
ExcelJiaochengShiyongjiqiaoXilie/css/normalize.css
ExcelJiaochengShiyongjiqiaoXilie/css/popup.css
ExcelJiaochengShiyongjiqiaoXilie/font/__init__.py
ExcelJiaochengShiyongjiqiaoXilie/font/fontello.eot
ExcelJiaochengShiyongjiqiaoXilie/font/fontello.svg
ExcelJiaochengShiyongjiqiaoXilie/font/fontello.ttf
ExcelJiaochengShiyongjiqiaoXilie/font/fontello.woff
ExcelJiaochengShiyongjiqiaoXilie/img/__init__.py
ExcelJiaochengShiyongjiqiaoXilie/img/annotator-glyph-sprite.png
ExcelJiaochengShiyongjiqiaoXilie/img/annotator-icon-sprite.png
ExcelJiaochengShiyongjiqiaoXilie/img/apple-touch-icon.png
ExcelJiaochengShiyongjiqiaoXilie/img/cancelfullscreen.png
ExcelJiaochengShiyongjiqiaoXilie/img/close.png
ExcelJiaochengShiyongjiqiaoXilie/img/fullscreen.png
ExcelJiaochengShiyongjiqiaoXilie/img/loader.gif
ExcelJiaochengShiyongjiqiaoXilie/img/menu-icon.png
ExcelJiaochengShiyongjiqiaoXilie/img/save.png
ExcelJiaochengShiyongjiqiaoXilie/img/saved.png
ExcelJiaochengShiyongjiqiaoXilie/img/settings-s.png
ExcelJiaochengShiyongjiqiaoXilie/img/settings.png
ExcelJiaochengShiyongjiqiaoXilie/img/star.png
ExcelJiaochengShiyongjiqiaoXilie/js/__init__.py
ExcelJiaochengShiyongjiqiaoXilie/js/epub.js
ExcelJiaochengShiyongjiqiaoXilie/js/epub.min.js
ExcelJiaochengShiyongjiqiaoXilie/js/epub.min.map
ExcelJiaochengShiyongjiqiaoXilie/js/hooks.min.js
ExcelJiaochengShiyongjiqiaoXilie/js/hooks.min.map
ExcelJiaochengShiyongjiqiaoXilie/js/reader.js
ExcelJiaochengShiyongjiqiaoXilie/js/reader.js.map
ExcelJiaochengShiyongjiqiaoXilie/js/reader.min.js
ExcelJiaochengShiyongjiqiaoXilie/js/reader.min.map
ExcelJiaochengShiyongjiqiaoXilie/js/hooks/__init__.py
excel_jiaocheng_shiyongjiqiao_xilie-2024.3.2.0.dist-info/METADATA
excel_jiaocheng_shiyongjiqiao_xilie-2024.3.2.0.dist-info/WHEEL
excel_jiaocheng_shiyongjiqiao_xilie-2024.3.2.0.dist-info/entry_points.txt
excel_jiaocheng_shiyongjiqiao_xilie-2024.3.2.0.dist-info/top_level.txt
excel_jiaocheng_shiyongjiqiao_xilie-2024.3.2.0.dist-info/RECORD
